{
  "type_description_msg": {
    "type_description": {
      "type_name": "ros2_fndm_interface/action/Fibonacci_SendGoal",
      "fields": [
        {
          "name": "request_message",
          "type": {
            "type_id": 1,
            "capacity": 0,
            "string_capacity": 0,
            "nested_type_name": "ros2_fndm_interface/action/Fibonacci_SendGoal_Request"
          },
          "default_value": ""
        },
        {
          "name": "response_message",
          "type": {
            "type_id": 1,
            "capacity": 0,
            "string_capacity": 0,
            "nested_type_name": "ros2_fndm_interface/action/Fibonacci_SendGoal_Response"
          },
          "default_value": ""
        },
        {
          "name": "event_message",
          "type": {
            "type_id": 1,
            "capacity": 0,
            "string_capacity": 0,
            "nested_type_name": "ros2_fndm_interface/action/Fibonacci_SendGoal_Event"
          },
          "default_value": ""
        }
      ]
    },
    "referenced_type_descriptions": [
      {
        "type_name": "builtin_interfaces/msg/Time",
        "fields": [
          {
            "name": "sec",
            "type": {
              "type_id": 6,
              "capacity": 0,
              "string_capacity": 0,
              "nested_type_name": ""
            },
            "default_value": ""
          },
          {
            "name": "nanosec",
            "type": {
              "type_id": 7,
              "capacity": 0,
              "string_capacity": 0,
              "nested_type_name": ""
            },
            "default_value": ""
          }
        ]
      },
      {
        "type_name": "ros2_fndm_interface/action/Fibonacci_Goal",
        "fields": [
          {
            "name": "order",
            "type": {
              "type_id": 8,
              "capacity": 0,
              "string_capacity": 0,
              "nested_type_name": ""
            },
            "default_value": ""
          }
        ]
      },
      {
        "type_name": "ros2_fndm_interface/action/Fibonacci_SendGoal_Event",
        "fields": [
          {
            "name": "info",
            "type": {
              "type_id": 1,
              "capacity": 0,
              "string_capacity": 0,
              "nested_type_name": "service_msgs/msg/ServiceEventInfo"
            },
            "default_value": ""
          },
          {
            "name": "request",
            "type": {
              "type_id": 97,
              "capacity": 1,
              "string_capacity": 0,
              "nested_type_name": "ros2_fndm_interface/action/Fibonacci_SendGoal_Request"
            },
            "default_value": ""
          },
          {
            "name": "response",
            "type": {
              "type_id": 97,
              "capacity": 1,
              "string_capacity": 0,
              "nested_type_name": "ros2_fndm_interface/action/Fibonacci_SendGoal_Response"
            },
            "default_value": ""
          }
        ]
      },
      {
        "type_name": "ros2_fndm_interface/action/Fibonacci_SendGoal_Request",
        "fields": [
          {
            "name": "goal_id",
            "type": {
              "type_id": 1,
              "capacity": 0,
              "string_capacity": 0,
              "nested_type_name": "unique_identifier_msgs/msg/UUID"
            },
            "default_value": ""
          },
          {
            "name": "goal",
            "type": {
              "type_id": 1,
              "capacity": 0,
              "string_capacity": 0,
              "nested_type_name": "ros2_fndm_interface/action/Fibonacci_Goal"
            },
            "default_value": ""
          }
        ]
      },
      {
        "type_name": "ros2_fndm_interface/action/Fibonacci_SendGoal_Response",
        "fields": [
          {
            "name": "accepted",
            "type": {
              "type_id": 15,
              "capacity": 0,
              "string_capacity": 0,
              "nested_type_name": ""
            },
            "default_value": ""
          },
          {
            "name": "stamp",
            "type": {
              "type_id": 1,
              "capacity": 0,
              "string_capacity": 0,
              "nested_type_name": "builtin_interfaces/msg/Time"
            },
            "default_value": ""
          }
        ]
      },
      {
        "type_name": "service_msgs/msg/ServiceEventInfo",
        "fields": [
          {
            "name": "event_type",
            "type": {
              "type_id": 3,
              "capacity": 0,
              "string_capacity": 0,
              "nested_type_name": ""
            },
            "default_value": ""
          },
          {
            "name": "stamp",
            "type": {
              "type_id": 1,
              "capacity": 0,
              "string_capacity": 0,
              "nested_type_name": "builtin_interfaces/msg/Time"
            },
            "default_value": ""
          },
          {
            "name": "client_gid",
            "type": {
              "type_id": 51,
              "capacity": 16,
              "string_capacity": 0,
              "nested_type_name": ""
            },
            "default_value": ""
          },
          {
            "name": "sequence_number",
            "type": {
              "type_id": 8,
              "capacity": 0,
              "string_capacity": 0,
              "nested_type_name": ""
            },
            "default_value": ""
          }
        ]
      },
      {
        "type_name": "unique_identifier_msgs/msg/UUID",
        "fields": [
          {
            "name": "uuid",
            "type": {
              "type_id": 51,
              "capacity": 16,
              "string_capacity": 0,
              "nested_type_name": ""
            },
            "default_value": ""
          }
        ]
      }
    ]
  },
  "type_hashes": [
    {
      "type_name": "ros2_fndm_interface/action/Fibonacci_SendGoal",
      "hash_string": "RIHS01_13f661a2766b03a44576ecfcd1752d7ea642b3f4a5ee62ed3f833918fa750703"
    },
    {
      "type_name": "builtin_interfaces/msg/Time",
      "hash_string": "RIHS01_b106235e25a4c5ed35098aa0a61a3ee9c9b18d197f398b0e4206cea9acf9c197"
    },
    {
      "type_name": "ros2_fndm_interface/action/Fibonacci_Goal",
      "hash_string": "RIHS01_57277e730d02875f4ac2c9ed0bc35d85bccdb9430b161f30bf78359257ea2bce"
    },
    {
      "type_name": "ros2_fndm_interface/action/Fibonacci_SendGoal_Event",
      "hash_string": "RIHS01_72c8e480ca4031c470abfc0abd04ecb7466d5b8a278e8ccd7de171c0bca21352"
    },
    {
      "type_name": "ros2_fndm_interface/action/Fibonacci_SendGoal_Request",
      "hash_string": "RIHS01_731f21741806c82b5475852e285252e48166705b0a68f6be38cc7dc45f3beea9"
    },
    {
      "type_name": "ros2_fndm_interface/action/Fibonacci_SendGoal_Response",
      "hash_string": "RIHS01_6bad10f97e8686a6ce340ed97f20fe61bd0aa8bf5b082ee9b323e40ec3773eec"
    },
    {
      "type_name": "service_msgs/msg/ServiceEventInfo",
      "hash_string": "RIHS01_41bcbbe07a75c9b52bc96bfd5c24d7f0fc0a08c0cb7921b3373c5732345a6f45"
    },
    {
      "type_name": "unique_identifier_msgs/msg/UUID",
      "hash_string": "RIHS01_1b8e8aca958cbea28fe6ef60bf6c19b683c97a9ef60bb34752067d0f2f7ab437"
    }
  ]
}